boggle/boggle.py
boggle/test_boggle.py
boggle2/boggle.py
boggle2/boggle2.py
boggle2/test_boggle.py
boggle_checker-0.1.dist-info/DESCRIPTION.rst
boggle_checker-0.1.dist-info/METADATA
boggle_checker-0.1.dist-info/RECORD
boggle_checker-0.1.dist-info/WHEEL
boggle_checker-0.1.dist-info/metadata.json
boggle_checker-0.1.dist-info/top_level.txt
