Metadata-Version: 2.0
Name: boggle-checker
Version: 0.1
Summary: Boggle answer checker
Home-page: https://github.com/Gmiller290488/trial
Author: Gareth Miller
Author-email: gmiller290488@gmail.com
License: UNKNOWN
Platform: UNKNOWN
Classifier: Intended Audience :: Developers
Classifier: Operating System :: MacOS :: MacOS X
Classifier: Operating System :: Microsoft :: Windows
Classifier: Programming Language :: Python
Classifier: Programming Language :: Python :: 3
